lemmsk/__init__.py
lemmsk/data/lemmatization-sk.marisa
lemmsk-0.0.3.dist-info/entry_points.txt
lemmsk-0.0.3.dist-info/DESCRIPTION.rst
lemmsk-0.0.3.dist-info/WHEEL
lemmsk-0.0.3.dist-info/METADATA
lemmsk-0.0.3.dist-info/RECORD
lemmsk-0.0.3.dist-info/metadata.json
lemmsk-0.0.3.dist-info/top_level.txt
