Metadata-Version: 2.0
Name: lemmsk
Version: 0.0.3
Summary: An off the shelf lemmer (a module capable oflemmatization) for Slovak language 
Home-page: https://github.com/mrshu/mrshu/lemm-sk
Author: mr.Shu
Author-email: mr@shu.io
License: MIT
Keywords: lemmatization lemming slovak
Platform: UNKNOWN
Classifier: Development Status :: 3 - Alpha
Classifier: Intended Audience :: Developers
Classifier: License :: OSI Approved :: MIT License
Classifier: Natural Language :: Slovak
Classifier: Intended Audience :: Education
Classifier: Intended Audience :: Science/Research
Classifier: Topic :: Scientific/Engineering :: Artificial Intelligence
Classifier: Topic :: Text Processing :: Linguistic
Classifier: Programming Language :: Python :: 2
Classifier: Programming Language :: Python :: 2.6
Classifier: Programming Language :: Python :: 2.7
Classifier: Programming Language :: Python :: 3
Classifier: Programming Language :: Python :: 3.2
Classifier: Programming Language :: Python :: 3.3
Classifier: Programming Language :: Python :: 3.4
Requires-Dist: marisa-trie
